neuralib/dashboard/__init__.py
neuralib/dashboard/base.py
neuralib/dashboard/example.py
neuralib/dashboard/example_multi.py
neuralib/dashboard/tool.py
neuralib/dashboard/util.py
neuralib/dashboard/view_brain.py
neuralib/dashboard/examples/__init__.py
neuralib/dashboard/examples/__main__.py
neuralib/dashboard/examples/model.py
neuralib/dashboard/examples/view_all.py
neuralib/dashboard/examples/view_animal.py
neuralib/dashboard/examples/view_figure.py
neuralib/imglib/__init__.py
neuralib/imglib/array.py
neuralib/imglib/color.py
neuralib/imglib/io.py
neuralib/imglib/labeller.py
neuralib/imglib/norm.py
neuralib/imglib/transform.py
neuralib/io/__init__.py
neuralib/io/core.py
neuralib/io/csv_header.py
neuralib/io/dataset.py
neuralib/io/json.py
neuralib/io/output.py
neuralib/io/pyh5.py
neuralib/persistence/__init__.py
neuralib/persistence/cli_persistence.py
neuralib/persistence/persistence.py
neuralib/persistence/validator.py
neuralib/plot/__init__.py
neuralib/plot/_dotplot.py
neuralib/plot/colormap.py
neuralib/plot/figure.py
neuralib/plot/plot.py
neuralib/plot/psth.py
neuralib/plot/tools.py
neuralib/plot/venn.py
neuralib/tools/__init__.py
neuralib/tools/gspread.py
neuralib/tools/slack_bot.py
neuralib/typing/__init__.py
neuralib/typing/alias.py
neuralib/typing/func.py
neuralib/util/__init__.py
neuralib/util/dataframe.py
neuralib/util/deprecation.py
neuralib/util/func.py
neuralib/util/gpu.py
neuralib/util/interp.py
neuralib/util/logging.py
neuralib/util/profile.py
neuralib/util/segments.py
neuralib/util/table.py
neuralib/util/tqdm.py
neuralib/util/unstable.py
neuralib/util/utils.py
neuralib/util/verbose.py
neuralib_utils-0.7.1.dist-info/licenses/LICENSE
neuralib_utils-0.7.1.dist-info/METADATA
neuralib_utils-0.7.1.dist-info/WHEEL
neuralib_utils-0.7.1.dist-info/top_level.txt
neuralib_utils-0.7.1.dist-info/RECORD
