Metadata-Version: 2.4
Name: neuralib-utils
Version: 0.7.1
Summary: Utilities for neuralib
Author-email: Yu-Ting Wei <ytsimon2004@gmail.com>
License: BSD 3-Clause License
Project-URL: Homepage, https://github.com/ytsimon2004/neuralib2
Project-URL: Documentation, https://neuralib2.readthedocs.io/en/latest/index.html
Project-URL: Repository, https://github.com/ytsimon2004/neuralib2
Project-URL: Issues, https://github.com/ytsimon2004/neuralib2/issues
Keywords: Utilies
Classifier: Programming Language :: Python :: 3.11
Classifier: Programming Language :: Python :: 3.12
Classifier: License :: OSI Approved :: BSD License
Classifier: Natural Language :: English
Classifier: Operating System :: OS Independent
Classifier: Topic :: Scientific/Engineering
Classifier: Intended Audience :: Science/Research
Classifier: Typing :: Typed
Requires-Python: <3.13,>=3.11
License-File: LICENSE
Requires-Dist: attrs>=25.3.0
Requires-Dist: numpy>=2.0
Requires-Dist: scipy
Requires-Dist: pandas
Requires-Dist: polars
Requires-Dist: pyarrow
Requires-Dist: h5py
Requires-Dist: rich
Requires-Dist: tqdm
Requires-Dist: typing_extensions
Requires-Dist: gdown
Provides-Extra: dashboard
Requires-Dist: bokeh; extra == "dashboard"
Provides-Extra: plot
Requires-Dist: seaborn>=0.13.2; extra == "plot"
Requires-Dist: matplotlib_venn>=1.1.2; extra == "plot"
Requires-Dist: matplotlib>=3.10.3; extra == "plot"
Provides-Extra: opt
Requires-Dist: colorama>=0.4.6; extra == "opt"
Requires-Dist: colorlog; extra == "opt"
Requires-Dist: gspread; extra == "opt"
Requires-Dist: slackclient; extra == "opt"
Requires-Dist: psutil; extra == "opt"
Requires-Dist: opencv-python; extra == "opt"
Requires-Dist: scikit-image; extra == "opt"
Requires-Dist: tiffile; extra == "opt"
Provides-Extra: all
Requires-Dist: neuralib-utils[plot]; extra == "all"
Requires-Dist: neuralib-utils[opt]; extra == "all"
Provides-Extra: test
Requires-Dist: neuralib-utils[dashboard]; extra == "test"
Requires-Dist: neuralib-utils[all]; extra == "test"
Dynamic: license-file
